setup.py
dodo_deploy_commands/__init__.py
dodo_deploy_commands/_utils.py
dodo_deploy_commands/ansible-deploy.py
dodo_deploy_commands/salt-deploy.py
dodo_deploy_commands/ssh-agent.py
dodo_deploy_commands.egg-info/PKG-INFO
dodo_deploy_commands.egg-info/SOURCES.txt
dodo_deploy_commands.egg-info/dependency_links.txt
dodo_deploy_commands.egg-info/not-zip-safe
dodo_deploy_commands.egg-info/top_level.txt
dodo_deploy_commands/drop-in/README.md
dodo_deploy_commands/drop-in/drop.off.yaml
dodo_deploy_commands/drop-in/drop.on.yaml
dodo_deploy_commands/drop-in/deploy-tools/docker/Dockerfile
dodo_deploy_commands/drop-in/ssh-agent/docker/Dockerfile