Metadata-Version: 1.1
Name: dodo-deploy-commands
Version: 0.1.3
Summary: Deployment related Dodo Commands
Home-page: https://github.com/mnieber/dodo_deploy_commands
Author: Maarten Nieber
Author-email: hallomaarten@yahoo.com
License: MIT
Download-URL: https://github.com/mnieber/dodo_deploy_commands/tarball/0.1.3
Platform: UNKNOWN
